hera_cli_utils/__init__.py
hera_cli_utils/logging.py
hera_cli_utils/profiling.py
hera_cli_utils/py.typed
hera_cli_utils-0.1.0.dist-info/METADATA
hera_cli_utils-0.1.0.dist-info/LICENSE
hera_cli_utils-0.1.0.dist-info/WHEEL
hera_cli_utils-0.1.0.dist-info/entry_points.txt
hera_cli_utils-0.1.0.dist-info/RECORD
