Metadata-Version: 2.1
Name: hera-cli-utils
Version: 0.1.0
Summary: HERA CLI Utils
Home-page: https://github.com/steven-murray/hera-cli-utils
License: MIT
Author: Steven Murray
Author-email: steven.g.murray@asu.edu
Requires-Python: >=3.7,<4.0
Classifier: Development Status :: 2 - Pre-Alpha
Classifier: License :: OSI Approved :: MIT License
Classifier: Programming Language :: Python :: 3
Classifier: Programming Language :: Python :: 3.7
Classifier: Programming Language :: Python :: 3.8
Classifier: Programming Language :: Python :: 3.9
Classifier: Programming Language :: Python :: 3.10
Classifier: Programming Language :: Python :: 3.11
Requires-Dist: click (>=8.0.1)
Requires-Dist: line-profiler (>=4.0.3,<5.0.0)
Requires-Dist: psutil (>=5.9.5,<6.0.0)
Requires-Dist: rich (>=13.4.2,<14.0.0)
Project-URL: Changelog, https://github.com/steven-murray/hera-cli-utils/releases
Project-URL: Documentation, https://hera-cli-utils.readthedocs.io
Project-URL: Repository, https://github.com/steven-murray/hera-cli-utils
